{"expireTime":9007200803979230000,"key":"transformer-remark-markdown-ast-dbc7308cc402d0daf3bff5a3a03f5700-gatsby-remark-prismjs-","val":{"type":"root","children":[{"type":"paragraph","children":[{"type":"text","value":"New design, content and some new CSS tricks on my website.","position":{"start":{"line":1,"column":1,"offset":0},"end":{"line":1,"column":59,"offset":58},"indent":[]}}],"position":{"start":{"line":1,"column":1,"offset":0},"end":{"line":1,"column":59,"offset":58},"indent":[]}}],"position":{"start":{"line":1,"column":1,"offset":0},"end":{"line":1,"column":59,"offset":58}}}}